{"stats":{"minecraft:dropped":{"minecraft:iron_ingot":5},"minecraft:picked_up":{"minecraft:poppy":1,"minecraft:armadillo_scute":1,"minecraft:brown_egg":1,"minecraft:iron_ingot":5},"minecraft:custom":{"minecraft:sprint_one_cm":29555,"minecraft:time_since_rest":150016,"minecraft:walk_one_cm":19724,"minecraft:total_world_time":150016,"minecraft:leave_game":8,"minecraft:fly_one_cm":231834,"minecraft:crouch_one_cm":1601,"minecraft:sneak_time":859,"minecraft:play_time":150016,"minecraft:jump":448,"minecraft:time_since_death":150016,"minecraft:drop":1},"minecraft:used":{"minecraft:grass_block":4}},"DataVersion":4440}